{
  "id": "performance/Optimize_Animation",
  "title": "Optimize_Animation",
  "description": "title: HTML5 Canvas Optimize Animation Performance Tip",
  "source": "@site/content/performance/Optimize_Animation.md",
  "sourceDirName": "performance",
  "slug": "/performance/Optimize_Animation",
  "permalink": "/performance/Optimize_Animation",
  "draft": false,
  "unlisted": false,
  "editUrl": "https://github.com/konvajs/site/tree/new/content/performance/Optimize_Animation.md",
  "tags": [],
  "version": "current",
  "frontMatter": {}
}